LICENSE
MANIFEST.in
README.md
requirements.txt
setup.cfg
setup.py
django_novaposhta.egg-info/PKG-INFO
django_novaposhta.egg-info/SOURCES.txt
django_novaposhta.egg-info/dependency_links.txt
django_novaposhta.egg-info/requires.txt
django_novaposhta.egg-info/top_level.txt
novaposhta/__init__.py
novaposhta/admin.py
novaposhta/lib.py
novaposhta/models.py
novaposhta/settings.py
novaposhta/translation.py
novaposhta/urls.py
novaposhta/views.py
novaposhta/locale/en/LC_MESSAGES/django.mo
novaposhta/locale/en/LC_MESSAGES/django.po
novaposhta/locale/ru/LC_MESSAGES/django.mo
novaposhta/locale/ru/LC_MESSAGES/django.po
novaposhta/locale/uk/LC_MESSAGES/django.mo
novaposhta/locale/uk/LC_MESSAGES/django.po
novaposhta/migrations/0001_initial.py
novaposhta/migrations/0002_model_translation.py
novaposhta/migrations/__init__.py