Metadata-Version: 1.1
Name: django-novaposhta
Version: 2.2
Summary: Django nova poshta ua api app
Home-page: https://github.com/pmaigutyak/mp-novaposhta
Author: Paul Maigutyak
Author-email: pmaigutyak@gmail.com
License: MIT
Download-URL: https://github.com/pmaigutyak/mp-novaposhta/archive/2.2.tar.gz
Platform: UNKNOWN
